kiraML/__init__.py
kiraML/_version.py
kiraML/kiraMLFunctions.py
kiraML-0.1.7.dist-info/LICENSE.md
kiraML-0.1.7.dist-info/METADATA
kiraML-0.1.7.dist-info/WHEEL
kiraML-0.1.7.dist-info/top_level.txt
kiraML-0.1.7.dist-info/RECORD
