Metadata-Version: 2.1
Name: kiraML
Version: 0.1.7
Summary: The KiraML library
Author: Kira Learning
License: MIT
License-File: LICENSE.md
Requires-Dist: scikit-learn
Requires-Dist: matplotlib
